proxy/__init__.py
proxy/models.py
proxy/tests.py
proxy/urls.py
proxy/views.py
proxy/__pycache__/__init__.cpython-310.pyc
proxy/__pycache__/models.cpython-310.pyc
proxy/__pycache__/tests.cpython-310.pyc
proxy/__pycache__/views.cpython-310.pyc
django_proxy-1.3.0.dist-info/METADATA
django_proxy-1.3.0.dist-info/WHEEL
django_proxy-1.3.0.dist-info/top_level.txt
django_proxy-1.3.0.dist-info/RECORD
