Metadata-Version: 2.1
Name: django-proxy
Version: 1.3.0
Summary: A simple HTTP proxy service as a Django app
Home-page: https://github.com/mjumbewu/django-proxy
Author: Mjumbe Wawatu Ukweli
Author-email: mjumbewu@gmail.com
License: BSD
Classifier: Development Status :: 4 - Beta
Classifier: Environment :: Web Environment
Classifier: Intended Audience :: Developers
Classifier: License :: OSI Approved :: BSD License
Classifier: Operating System :: OS Independent
Classifier: Programming Language :: Python
Classifier: Programming Language :: Python :: 3
Classifier: Framework :: Django
Requires-Dist: requests
